certs/cacert.pem
tol/__init__.py
tol/markdown.py
tol/actions/__init__.py
tol/actions/action.py
tol/actions/upsert_action.py
tol/api_base/__init__.py
tol/api_base/action.py
tol/api_base/blueprint.py
tol/api_base/controller.py
tol/api_base/data_upload.py
tol/api_base/pipeline_steps.py
tol/api_base/system.py
tol/api_base/auth/__init__.py
tol/api_base/auth/asserts.py
tol/api_base/auth/blueprint.py
tol/api_base/auth/composite.py
tol/api_base/auth/config.py
tol/api_base/auth/error.py
tol/api_base/auth/abc/__init__.py
tol/api_base/auth/abc/auth.py
tol/api_base/auth/abc/authorisation.py
tol/api_base/misc/__init__.py
tol/api_base/misc/aggregation_body.py
tol/api_base/misc/aggregation_parameters.py
tol/api_base/misc/auth_context.py
tol/api_base/misc/authenticate.py
tol/api_base/misc/data_body.py
tol/api_base/misc/filter_utils.py
tol/api_base/misc/list_get_parameters.py
tol/api_base/misc/relation_url.py
tol/api_base/misc/stats_parameters.py
tol/api_client/__init__.py
tol/api_client/api_datasource.py
tol/api_client/client.py
tol/api_client/converter.py
tol/api_client/exception.py
tol/api_client/factory.py
tol/api_client/filter.py
tol/api_client/parser.py
tol/api_client/validate.py
tol/api_client/view.py
tol/barcodes/__init__.py
tol/barcodes/main.py
tol/benchling/__init__.py
tol/benchling/benchling_converter.py
tol/benchling/benchling_datasource.py
tol/benchling/benchling_warehouse_datasource.py
tol/benchling/sql/__init__.py
tol/benchling/sql/extraction_containers_dna.sql
tol/benchling/sql/extraction_extraction_type_dna.sql
tol/benchling/sql/extraction_extraction_type_lres.sql
tol/benchling/sql/extraction_extraction_type_pooled_dna.sql
tol/benchling/sql/extraction_extraction_type_rna.sql
tol/benchling/sql/pacbio_prep.sql
tol/benchling/sql/pooled_pacbio_prep.sql
tol/benchling/sql/results_extraction_dna.sql
tol/benchling/sql/results_extraction_pooled.sql
tol/benchling/sql/results_extraction_rna.sql
tol/benchling/sql/results_pacbio_prep.sql
tol_sdk-1.8.2.dist-info/licenses/LICENSE
tol_sdk-1.8.2.dist-info/METADATA
tol_sdk-1.8.2.dist-info/WHEEL
tol_sdk-1.8.2.dist-info/entry_points.txt
tol_sdk-1.8.2.dist-info/top_level.txt
tol_sdk-1.8.2.dist-info/RECORD
